Questionare/__init__.py
questionare-0.0.2.dist-info/LICENSE
questionare-0.0.2.dist-info/METADATA
questionare-0.0.2.dist-info/WHEEL
questionare-0.0.2.dist-info/top_level.txt
questionare-0.0.2.dist-info/RECORD
