Metadata-Version: 2.1
Name: questionare
Version: 0.0.2
Summary: Easiest way to make a simple survey!
Home-page: https://github.com/CraftYun83/Questionare
Author: CraftYun83
Author-email: craftyun83@gmail.com
License: UNKNOWN
Platform: UNKNOWN
Classifier: Programming Language :: Python :: 3
Classifier: License :: OSI Approved :: MIT License
Classifier: Operating System :: OS Independent
Requires-Python: >=3.6
